soga_ai/__init__.py
soga_ai/client.py
soga_ai/config.py
soga_ai/decorators.py
soga_ai/models.py
soga_ai/protocols/__init__.py
soga_ai/protocols/base.py
soga_ai/protocols/edge.py
soga_ai/protocols/google.py
soga_ai/protocols/modelscope.py
soga_ai/protocols/openai.py
soga_ai/protocols/runway.py
soga_ai-0.1.11.dist-info/METADATA
soga_ai-0.1.11.dist-info/WHEEL
soga_ai-0.1.11.dist-info/top_level.txt
soga_ai-0.1.11.dist-info/RECORD
