Metadata-Version: 2.4
Name: soga_ai
Version: 0.1.11
Summary: A Python library that encapsulates AI model APIs
Author-email: Your Name <your.email@example.com>
License-Expression: MIT
Classifier: Development Status :: 3 - Alpha
Classifier: Intended Audience :: Developers
Classifier: Programming Language :: Python :: 3
Classifier: Programming Language :: Python :: 3.10
Requires-Python: >=3.10
Requires-Dist: edge-tts>=6.1.12
Requires-Dist: httpx[socks]>=0.28.1
Requires-Dist: openai>=1.97.1
Requires-Dist: pytest>=8.4.1
Requires-Dist: pytest-mock>=3.14.1
Requires-Dist: requests>=2.32.4
Requires-Dist: runwayapi>=0.2.1
